MANIFEST.in
setup.cfg
setup.py
g1fitting/Clothoid.cpp
g1fitting/Clothoid.h
g1fitting/__init__.py
g1fitting/g1fittingmodule.cpp
g1fitting/test.py
g1fitting.egg-info/PKG-INFO
g1fitting.egg-info/SOURCES.txt
g1fitting.egg-info/dependency_links.txt
g1fitting.egg-info/top_level.txt