Metadata-Version: 1.1
Name: g1fitting
Version: 0.1.2
Summary: A package to create and sample C1 continuous clothoid curves.
Home-page: https://github.com/ozymandium/g1fitting
Author: Robert Cofield
Author-email: robertgcofield@gmail.com
License: UNKNOWN
Download-URL: https://github.com/ozymandium/g1fitting/tarball/pypi
Keywords: clothoid,curvature,curve,fitting
Platform: UNKNOWN
